asas_egb/__init__.py
asas_egb/annotation.py
asas_egb/component.py
asas_egb/db.py
asas_egb/inference.py
asas_egb/message.py
asas_egb/pe_utils.py
asas_egb/plot.py
asas_egb/result.py
asas_egb/run.py
asas_egb/stats.py
asas_egb/task/__init__.py
asas_egb/task/align.py
asas_egb/task/inference.py
asas_egb/task/plot.py
asas_egb/task/result.py
asas_egb/task/task.py
asas_egb-1.0.0.dist-info/DESCRIPTION.rst
asas_egb-1.0.0.dist-info/METADATA
asas_egb-1.0.0.dist-info/RECORD
asas_egb-1.0.0.dist-info/WHEEL
asas_egb-1.0.0.dist-info/entry_points.txt
asas_egb-1.0.0.dist-info/metadata.json
asas_egb-1.0.0.dist-info/top_level.txt
