Metadata-Version: 2.0
Name: asas-egb
Version: 1.0.0
Summary: A library for estimating allele-specific alternative splicing events using transcriptome data
Home-page: https://github.com/ncjllld/asas-egb
Author: Lili Dong
Author-email: ncjllld@hit.edu.cn
Classifier: Programming Language :: Python :: 3
Classifier: License :: OSI Approved :: GNU General Public License v3 (GPLv3)
Classifier: Operating System :: OS Independent
Requires-Python: >=3.7
License-File: LICENSE
